raft_toolkit/__init__.py
raft_toolkit/cli/__init__.py
raft_toolkit/cli/main.py
raft_toolkit/core/__init__.py
raft_toolkit/core/config.py
raft_toolkit/core/models.py
raft_toolkit/core/raft_engine.py
raft_toolkit/core/security.py
raft_toolkit/core/clients/__init__.py
raft_toolkit/core/clients/openai_client.py
raft_toolkit/core/clients/stats.py
raft_toolkit/core/formatters/__init__.py
raft_toolkit/core/formatters/dataset_converter.py
raft_toolkit/core/logging/__init__.py
raft_toolkit/core/logging/setup.py
raft_toolkit/core/services/__init__.py
raft_toolkit/core/services/dataset_service.py
raft_toolkit/core/services/document_service.py
raft_toolkit/core/services/embedding_service.py
raft_toolkit/core/services/input_service.py
raft_toolkit/core/services/langwatch_service.py
raft_toolkit/core/services/llm_service.py
raft_toolkit/core/sources/__init__.py
raft_toolkit/core/sources/base.py
raft_toolkit/core/sources/factory.py
raft_toolkit/core/sources/local.py
raft_toolkit/core/sources/s3.py
raft_toolkit/core/sources/sharepoint.py
raft_toolkit/core/utils/__init__.py
raft_toolkit/core/utils/env_config.py
raft_toolkit/core/utils/file_utils.py
raft_toolkit/core/utils/identity_utils.py
raft_toolkit/core/utils/rate_limiter.py
raft_toolkit/core/utils/template_loader.py
raft_toolkit/templates/default_answer_template.txt
raft_toolkit/templates/default_embedding_template.txt
raft_toolkit/templates/default_qa_template.txt
raft_toolkit/templates/embedding_prompt_template.txt
raft_toolkit/templates/gpt_qa_template.txt
raft_toolkit/templates/gpt_template.txt
raft_toolkit/templates/llama_qa_template.txt
raft_toolkit/templates/llama_template.txt
raft_toolkit/templates/simple_answer_template.txt
raft_toolkit/templates/simple_qa_template.txt
raft_toolkit/tools/__init__.py
raft_toolkit/tools/answer.py
raft_toolkit/tools/eval.py
raft_toolkit/tools/pfeval_chat.py
raft_toolkit/tools/pfeval_completion.py
raft_toolkit/tools/pfeval_local.py
raft_toolkit/web/__init__.py
raft_toolkit/web/app.py
raft_toolkit-0.3.1.dist-info/METADATA
raft_toolkit-0.3.1.dist-info/WHEEL
raft_toolkit-0.3.1.dist-info/entry_points.txt
raft_toolkit-0.3.1.dist-info/top_level.txt
raft_toolkit-0.3.1.dist-info/RECORD
