Metadata-Version: 2.4
Name: raft-toolkit
Version: 0.3.1
Summary: RAFT (Retrieval Augmented Fine Tuning) toolkit for generating synthetic Q&A datasets
Author: RAFT Toolkit Team
License-Expression: MIT
Project-URL: Homepage, https://visland.com
Project-URL: Bug Reports, https://github.com/makercorn/raft-toolkit/issues
Project-URL: Source, https://github.com/makercorn/raft-toolkit
Classifier: Development Status :: 4 - Beta
Classifier: Intended Audience :: Developers
Classifier: Programming Language :: Python :: 3
Classifier: Programming Language :: Python :: 3.11
Classifier: Programming Language :: Python :: 3.12
Classifier: Operating System :: OS Independent
Classifier: Operating System :: POSIX :: Linux
Classifier: Operating System :: MacOS
Classifier: Operating System :: Microsoft :: Windows
Requires-Python: <3.14,>=3.11
Requires-Dist: pydantic<3.0.0,>=2.8.0
Requires-Dist: requests<3.0.0,>=2.32.0
Requires-Dist: python-dotenv<2.0.0,>=1.0.1
Requires-Dist: pyyaml<7.0.0,>=6.0.1
Requires-Dist: tenacity<9.0.0,>=8.5.0
Requires-Dist: tqdm<5.0.0,>=4.66.0
Requires-Dist: coloredlogs<16.0.0,>=15.0.1
Requires-Dist: openai<2.0.0,>=1.68.2
Requires-Dist: tiktoken<1.0.0,>=0.7.0
Requires-Dist: langchain-core<0.4.0,>=0.3.5
Requires-Dist: pandas<3.0.0,>=2.2.0
Requires-Dist: jsonlines<5.0.0,>=4.0.0
Requires-Dist: pypdf<5.0.0,>=4.3.0
Provides-Extra: ai
Requires-Dist: transformers<5.0.0,>=4.46.0; extra == "ai"
Requires-Dist: sentence-transformers<4.0.0,>=3.2.0; extra == "ai"
Requires-Dist: scikit-learn<2.0.0,>=1.5.0; extra == "ai"
Requires-Dist: datasets<4.0.0,>=3.0.0; extra == "ai"
Requires-Dist: pyarrow<18.0.0,>=17.0.0; extra == "ai"
Provides-Extra: langchain
Requires-Dist: langchain-openai<0.4.0,>=0.3.7; extra == "langchain"
Requires-Dist: langchain-community<0.4.0,>=0.3.7; extra == "langchain"
Requires-Dist: langchain-experimental<0.4.0,>=0.3.3; extra == "langchain"
Requires-Dist: langchain-text-splitters<0.4.0,>=0.3.2; extra == "langchain"
Provides-Extra: embeddings
Requires-Dist: nomic<4.0.0,>=3.1.0; extra == "embeddings"
Provides-Extra: documents
Requires-Dist: python-pptx<1.0.0,>=0.6.23; extra == "documents"
Requires-Dist: pdfplumber<1.0.0,>=0.11.0; extra == "documents"
Provides-Extra: web
Requires-Dist: fastapi<1.0.0,>=0.115.6; extra == "web"
Requires-Dist: starlette<1.0.0,>=0.41.0; extra == "web"
Requires-Dist: uvicorn[standard]<1.0.0,>=0.32.0; extra == "web"
Requires-Dist: python-multipart<1.0.0,>=0.0.18; extra == "web"
Requires-Dist: aiofiles<25.0.0,>=24.1.0; extra == "web"
Requires-Dist: redis<6.0.0,>=5.2.0; extra == "web"
Requires-Dist: celery<6.0.0,>=5.4.0; extra == "web"
Provides-Extra: kubernetes
Requires-Dist: kubernetes<31.0.0,>=30.1.0; extra == "kubernetes"
Requires-Dist: jinja2<4.0.0,>=3.1.4; extra == "kubernetes"
Requires-Dist: prometheus-client<1.0.0,>=0.21.0; extra == "kubernetes"
Provides-Extra: cloud
Requires-Dist: boto3<1.36.0,>=1.35.0; extra == "cloud"
Requires-Dist: botocore<1.36.0,>=1.35.0; extra == "cloud"
Requires-Dist: azure-identity<1.19.0,>=1.18.0; extra == "cloud"
Requires-Dist: azure-core<1.32.0,>=1.31.0; extra == "cloud"
Requires-Dist: azure-keyvault-secrets<4.9.0,>=4.8.0; extra == "cloud"
Requires-Dist: azure-storage-blob<12.25.0,>=12.23.0; extra == "cloud"
Requires-Dist: requests-oauthlib<1.4.0,>=1.3.1; extra == "cloud"
Requires-Dist: msal<1.32.0,>=1.31.0; extra == "cloud"
Provides-Extra: tracing
Requires-Dist: opentelemetry-api<2.0.0,>=1.32.1; extra == "tracing"
Requires-Dist: opentelemetry-sdk<2.0.0,>=1.32.1; extra == "tracing"
Requires-Dist: structlog<25.0.0,>=24.4.0; extra == "tracing"
Requires-Dist: sentry-sdk<3.0.0,>=2.17.0; extra == "tracing"
Requires-Dist: langwatch<0.5.0,>=0.2.0; extra == "tracing"
Provides-Extra: dev
Requires-Dist: pytest<9.0.0,>=8.3.0; extra == "dev"
Requires-Dist: pytest-asyncio<1.0.0,>=0.24.0; extra == "dev"
Requires-Dist: pytest-cov<7.0.0,>=6.0.0; extra == "dev"
Requires-Dist: pytest-mock<4.0.0,>=3.14.0; extra == "dev"
Requires-Dist: pytest-timeout<3.0.0,>=2.1.0; extra == "dev"
Requires-Dist: httpx<1.0.0,>=0.28.0; extra == "dev"
Requires-Dist: flake8<8.0.0,>=7.1.0; extra == "dev"
Requires-Dist: black<25.0.0,>=24.10.0; extra == "dev"
Requires-Dist: isort<6.0.0,>=5.13.0; extra == "dev"
Requires-Dist: mypy<2.0.0,>=1.13.0; extra == "dev"
Requires-Dist: types-requests<3.0.0,>=2.32.0; extra == "dev"
Requires-Dist: types-PyYAML<7.0.0,>=6.0.0; extra == "dev"
Requires-Dist: types-simplejson<4.0.0,>=3.20.0; extra == "dev"
Requires-Dist: types-ujson<6.0.0,>=5.10.0; extra == "dev"
Requires-Dist: bandit<2.0.0,>=1.8.0; extra == "dev"
Requires-Dist: safety<4.0.0,>=3.2.0; extra == "dev"
Provides-Extra: minimal
Requires-Dist: raft-toolkit[langchain]; extra == "minimal"
Provides-Extra: standard
Requires-Dist: raft-toolkit[ai,documents,embeddings,langchain]; extra == "standard"
Provides-Extra: complete
Requires-Dist: raft-toolkit[ai,cloud,documents,embeddings,langchain,tracing]; extra == "complete"
Provides-Extra: all
Requires-Dist: raft-toolkit[ai,cloud,dev,documents,embeddings,kubernetes,langchain,tracing,web]; extra == "all"
